.DS_Store
fusion_utils/__init__.py
fusion_utils/errors.py
fusion_utils/fusion_logger.py
fusion_utils/pipeline.py
fusion_utils/slackbot.py
fusion_utils/task.py
fusion_utils-1.5.5.dist-info/METADATA
fusion_utils-1.5.5.dist-info/WHEEL
fusion_utils-1.5.5.dist-info/top_level.txt
fusion_utils-1.5.5.dist-info/RECORD
