Metadata-Version: 2.1
Name: fusion_utils
Version: 1.5.5
Summary: A utility package Fusion 2.0
Home-page: https://github.com/dylandoyle11/fusion_utils
Author: Dylan D
Author-email: dylan.doyle@jdpa.com
Classifier: Programming Language :: Python :: 3
Classifier: License :: OSI Approved :: MIT License
Classifier: Operating System :: OS Independent
Requires-Dist: pandas
Requires-Dist: google-cloud-bigquery
Requires-Dist: numpy
Requires-Dist: slack-sdk
